twapi/__init__.py
twapi/twapi.py
twapi-0.0.2.dist-info/LICENSE
twapi-0.0.2.dist-info/METADATA
twapi-0.0.2.dist-info/WHEEL
twapi-0.0.2.dist-info/top_level.txt
twapi-0.0.2.dist-info/RECORD
